jupyter_francy/__init__.py
jupyter_francy/_version.py
jupyter_francy/labextension/LICENSE
jupyter_francy/labextension/README.md
jupyter_francy/labextension/extension.js
jupyter_francy/labextension/package.json
jupyter_francy/labextension/yarn.lock
jupyter_francy/labextension/node_modules/.yarn-integrity
jupyter_francy/nbextension/D3Renderer.js
jupyter_francy/nbextension/FrancyJS.js
jupyter_francy/nbextension/GraphvizRenderer.js
jupyter_francy/nbextension/Vendors.js
jupyter_francy/nbextension/VisRenderer.js
jupyter_francy/nbextension/extension.js
jupyter_francy/nbextension/index.js
jupyter_francy-1.2.4.data/data/share/jupyter/lab/extensions/extension.js
jupyter_francy-1.2.4.data/data/share/jupyter/lab/extensions/package.json
jupyter_francy-1.2.4.data/data/share/jupyter/nbextensions/jupyter_francy/D3Renderer.js
jupyter_francy-1.2.4.data/data/share/jupyter/nbextensions/jupyter_francy/FrancyJS.js
jupyter_francy-1.2.4.data/data/share/jupyter/nbextensions/jupyter_francy/GraphvizRenderer.js
jupyter_francy-1.2.4.data/data/share/jupyter/nbextensions/jupyter_francy/Vendors.js
jupyter_francy-1.2.4.data/data/share/jupyter/nbextensions/jupyter_francy/VisRenderer.js
jupyter_francy-1.2.4.data/data/share/jupyter/nbextensions/jupyter_francy/extension.js
jupyter_francy-1.2.4.data/data/share/jupyter/nbextensions/jupyter_francy/index.js
jupyter_francy-1.2.4.dist-info/LICENSE
jupyter_francy-1.2.4.dist-info/METADATA
jupyter_francy-1.2.4.dist-info/WHEEL
jupyter_francy-1.2.4.dist-info/top_level.txt
jupyter_francy-1.2.4.dist-info/RECORD
