Metadata-Version: 2.1
Name: jupyter-francy
Version: 1.2.4
Summary: UNKNOWN
Home-page: http://jupyter.org
Author: Manuel Martins
Author-email: manuelmachadomartins@gmail.com
License: BSD
Keywords: ipython,jupyter,francy,gap
Platform: Linux
Platform: Mac OS X
Platform: Windows
Classifier: Intended Audience :: Developers
Classifier: Intended Audience :: System Administrators
Classifier: Intended Audience :: Science/Research
Classifier: License :: OSI Approved :: BSD License
Classifier: Programming Language :: Python
Classifier: Programming Language :: Python :: 2.7
Classifier: Programming Language :: Python :: 3
Classifier: Programming Language :: Python :: 3.3
Classifier: Programming Language :: Python :: 3.4
Classifier: Programming Language :: Python :: 3.5
Requires-Dist: notebook (>=4.3.0)
